<?xml version="1.0" encoding="utf-8" ?>
<LanguageData>

	<!-- Artistic recipes - speed not affected by skill.-->

	<SculptingSpeed.label>скорость ваяния</SculptingSpeed.label>
	<SculptingSpeed.description>Скорость, с которой личность создаёт скульптуры. Обратите внимание: Навык влияет на качество созданой скульптуры, а не на скорость её создания.</SculptingSpeed.description>

	<TailoringSpeed.label>скорость шитья</TailoringSpeed.label>
	<TailoringSpeed.description>Скорость, с которой личность создаёт одежду. Обратите внимание: Навык влияет на качество одеяний, а не на скорость шитья.</TailoringSpeed.description>

	<SmithingSpeed.label>скорость ковки</SmithingSpeed.label>
	<SmithingSpeed.description>Скорость, с которой личность выковывает, либо изготавливает оружие, механизмы, боеприпасы и инструменты. Обратите Внимание: Навык влияет на качество созданных вещей, а не на скорость их создания.</SmithingSpeed.description>

	<!-- Production recipes - speed affected by skill.-->

	<DrugProductionSpeed.label>скорость создания химпрепаратов</DrugProductionSpeed.label>
	<DrugProductionSpeed.description>Насколько быстро личность производит медикаменты и наркотики.</DrugProductionSpeed.description>

	<CookSpeed.label>скорость готовки еды</CookSpeed.label>
	<CookSpeed.description>Скорость приготовления личностью блюд.</CookSpeed.description>

	<FoodPoisonChance.label>вероятность порчи еды</FoodPoisonChance.label>
	<FoodPoisonChance.description>Вероятность, что личность может ненароком сделать блюдо, которое готовит, непригодным в пищу.</FoodPoisonChance.description>

	<BrewingSpeed.label>скорость варки пива</BrewingSpeed.label>
	<BrewingSpeed.description>Скорость варки пива личностью.</BrewingSpeed.description>

	<ButcheryFleshSpeed.label>скорость разделки</ButcheryFleshSpeed.label>
	<ButcheryFleshSpeed.description>Скорость, с которой личность разделывает плоть существ.</ButcheryFleshSpeed.description>

	<ButcheryMechanoidSpeed.label>скорость разбора механоидов</ButcheryMechanoidSpeed.label>
	<ButcheryMechanoidSpeed.description>Скорость, с которой личность может разобрать механоида на части.</ButcheryMechanoidSpeed.description>

	<MechanoidOperationSuccessChance.label>успешность работы над механоидом</MechanoidOperationSuccessChance.label>
	<MechanoidOperationSuccessChance.description>Вероятность, что персонаж успешно завершит работу над механоидом. Результатом неудачи будут потеря добытых деталей и ранение самого механика.</MechanoidOperationSuccessChance.description>

	<ButcheryFleshEfficiency.label>полнота разделки</ButcheryFleshEfficiency.label>
	<ButcheryFleshEfficiency.description>Множитель количества мяса, получаемого при разделке существ из плоти.</ButcheryFleshEfficiency.description>

	<ButcheryMechanoidEfficiency.label>полнота разбора механоидов</ButcheryMechanoidEfficiency.label>
	<ButcheryMechanoidEfficiency.description>Множитель количества материалов, получаемых личностью при разборке мёртвого механоида.</ButcheryMechanoidEfficiency.description>

	<!-- Dumb recipes - not affected by skill because there's no skill component -->

	<SmeltingSpeed.label>скорость переплавки</SmeltingSpeed.label>
	<SmeltingSpeed.description>Скорость, с которой личность переплавляет что-либо. Обратите внимание: Поскольку для этой работы не нужны никакие навыки, на её скорость они не влияют.</SmeltingSpeed.description>

</LanguageData>
