<?xml version="1.0" encoding="utf-8" ?>
<LanguageData>

	<RaidEnemy.label>налёт</RaidEnemy.label>

	<Infestation.label>ивазия</Infestation.label>
	<Infestation.letterLabel>Инвазия</Infestation.letterLabel>
	<Infestation.letterText>Появилась колония жуков!\n\nВ ней потихоньку будут плодиться жуки, а также создаваться новые колонии. Если не желаете, чтобы жуками кишела вся местность, собирайте людей и уничтожте её. Но будьте осторожны: жуки будут защищать свою колонию.</Infestation.letterText>

	<ManhunterPack.label>стая животных-людоедов</ManhunterPack.label>

	<PsychicEmanatorShipPartCrash.label>падение части корабля (психо)</PsychicEmanatorShipPartCrash.label>
	<PsychicEmanatorShipPartCrash.letterLabel>Психокорабль</PsychicEmanatorShipPartCrash.letterLabel>
	<PsychicEmanatorShipPartCrash.letterText>Неподалёку упал крупный обломок древнего судна.\n\nВаши поселенцы, подталкиваемые к невыразимым словами действиям, подсозназнательно что-то чувствуют. Это должно быть бортовая ИИ-личность со способностью проецировать мысли прямо внутрь разума. И личность эта настроена не дружелюбно.\n\nУничтожьте её как можно скорее.</PsychicEmanatorShipPartCrash.letterText>

	<PoisonShipPartCrash.label>падение части корабля (яд)</PoisonShipPartCrash.label>
	<PoisonShipPartCrash.letterLabel>Ядовитое судно</PoisonShipPartCrash.letterLabel>
	<PoisonShipPartCrash.letterText>Неподалёку упал крупный обломок древнего судна.\n\nИз него сочатся токсины, уничтожая все растения всё дальше и дальше от обломка.\n\nУничтожьте обломок как можно скорее.</PoisonShipPartCrash.letterText>

	<AnimalInsanityMass.label>массовое помешательство животных</AnimalInsanityMass.label>

	<AnimalInsanitySingle.label>животное впало в безумие</AnimalInsanitySingle.label>

</LanguageData>
